{
    "id": 5100,
    "nome": "Alexandre Santos",
    "email": "bitcoinmakerbr@gmail.com",
    "usuario": "bitcoinmaker",
    "contato": "5511941678221",
    "patrocinador": "N/A",
    "entradas": {
        "entradas_totais": 10.0,
        "entradas_usdt": 0,
        "entradas_fakes": 0,
        "entradas_pix": 10.0
    },
    "saidas": {
        "saques_totais": 5.0,
        "saques_pix": 5.0,
        "saques_usdt": 0
    },
    "ganhos": {
        "ganhos_rendimento": 2.54,
        "ganhos_residual": 3.9
    },
    "primeiro_nivel": {
        "numero_indicados": 1,
        "total_normal": 1,
        "total_fake": 0,
        "total_bonus": 0,
        "total_lider": 0,
        "total_investido": 10.0,
        "total_pix": 10.0,
        "total_usdt": 0.0,
        "total_fakes": 0.0
    }
}