{
    "id": 4895,
    "nome": "Agenor Rocha Campos",
    "email": "agecamposrocha@gmail.com",
    "usuario": "AgenorAguia",
    "contato": "619991741511",
    "patrocinador": "N/A",
    "entradas": {
        "entradas_totais": 160.0,
        "entradas_usdt": 0,
        "entradas_fakes": 100.0,
        "entradas_pix": 60.0
    },
    "saidas": {
        "saques_totais": 0,
        "saques_pix": 0,
        "saques_usdt": 0
    },
    "ganhos": {
        "ganhos_rendimento": 38.19,
        "ganhos_residual": 4.12
    },
    "primeiro_nivel": {
        "numero_indicados": 4,
        "total_normal": 1,
        "total_fake": 0,
        "total_bonus": 0,
        "total_lider": 3,
        "total_investido": 320.0,
        "total_pix": 70.0,
        "total_usdt": 0.0,
        "total_fakes": 250.0
    }
}