{
    "nome": "Gilberto Rosa",
    "email": "gilbertof.r.001@gmail.com",
    "usuario": "Gilbertorosa",
    "contato": "64993429004",
    "tipo_conta": "LIDER",
    "saldo_disponivel": 12.94,
    "entradas": {
        "entradas_totais": 750.0,
        "entradas_usdt": 0,
        "entradas_fakes": 300.0,
        "entradas_pix": 450.0
    },
    "saidas": {
        "saques_totais": 40.0,
        "saques_pix": 40.0,
        "saques_usdt": 0
    },
    "ganhos": {
        "ganhos_rendimento": 52.94,
        "ganhos_residual": 0
    },
    "niveis": {
        "nivel_1": {
            "numero_indicados": 0,
            "total_normal": 0,
            "total_fake": 0,
            "total_bonus": 0,
            "total_lider": 0,
            "total_investido": 0.0,
            "total_pix": 0.0,
            "total_usdt": 0.0,
            "total_fakes": 0.0
        },
        "nivel_2": {
            "numero_indicados": 0,
            "total_normal": 0,
            "total_fake": 0,
            "total_bonus": 0,
            "total_lider": 0,
            "total_investido": 0.0,
            "total_pix": 0.0,
            "total_usdt": 0.0,
            "total_fakes": 0.0
        },
        "nivel_3": {
            "numero_indicados": 0,
            "total_normal": 0,
            "total_fake": 0,
            "total_bonus": 0,
            "total_lider": 0,
            "total_investido": 0.0,
            "total_pix": 0.0,
            "total_usdt": 0.0,
            "total_fakes": 0.0
        },
        "nivel_4": {
            "numero_indicados": 0,
            "total_normal": 0,
            "total_fake": 0,
            "total_bonus": 0,
            "total_lider": 0,
            "total_investido": 0.0,
            "total_pix": 0.0,
            "total_usdt": 0.0,
            "total_fakes": 0.0
        },
        "nivel_5": {
            "numero_indicados": 0,
            "total_normal": 0,
            "total_fake": 0,
            "total_bonus": 0,
            "total_lider": 0,
            "total_investido": 0.0,
            "total_pix": 0.0,
            "total_usdt": 0.0,
            "total_fakes": 0.0
        },
        "nivel_6": {
            "numero_indicados": 0,
            "total_normal": 0,
            "total_fake": 0,
            "total_bonus": 0,
            "total_lider": 0,
            "total_investido": 0.0,
            "total_pix": 0.0,
            "total_usdt": 0.0,
            "total_fakes": 0.0
        },
        "nivel_7": {
            "numero_indicados": 0,
            "total_normal": 0,
            "total_fake": 0,
            "total_bonus": 0,
            "total_lider": 0,
            "total_investido": 0.0,
            "total_pix": 0.0,
            "total_usdt": 0.0,
            "total_fakes": 0.0
        },
        "nivel_8": {
            "numero_indicados": 0,
            "total_normal": 0,
            "total_fake": 0,
            "total_bonus": 0,
            "total_lider": 0,
            "total_investido": 0.0,
            "total_pix": 0.0,
            "total_usdt": 0.0,
            "total_fakes": 0.0
        },
        "nivel_9": {
            "numero_indicados": 0,
            "total_normal": 0,
            "total_fake": 0,
            "total_bonus": 0,
            "total_lider": 0,
            "total_investido": 0.0,
            "total_pix": 0.0,
            "total_usdt": 0.0,
            "total_fakes": 0.0
        },
        "nivel_10": {
            "numero_indicados": 0,
            "total_normal": 0,
            "total_fake": 0,
            "total_bonus": 0,
            "total_lider": 0,
            "total_investido": 0.0,
            "total_pix": 0.0,
            "total_usdt": 0.0,
            "total_fakes": 0.0
        }
    }
}